embeddingframework/__init__.py
embeddingframework/cli.py
embeddingframework/adapters/__init__.py
embeddingframework/adapters/base.py
embeddingframework/adapters/chromadb_adapter.py
embeddingframework/adapters/faiss_adapter.py
embeddingframework/adapters/milvus_adapter.py
embeddingframework/adapters/openai_embedding_adapter.py
embeddingframework/adapters/pinecone_adapter.py
embeddingframework/adapters/providers.py
embeddingframework/adapters/storage.py
embeddingframework/adapters/vector_dbs.py
embeddingframework/adapters/vector_dbs_base.py
embeddingframework/adapters/weaviate_adapter.py
embeddingframework/adapters/storage/__init__.py
embeddingframework/adapters/storage/azure_blob_storage_adapter.py
embeddingframework/adapters/storage/gcs_storage_adapter.py
embeddingframework/adapters/storage/s3_storage_adapter.py
embeddingframework/processors/__init__.py
embeddingframework/processors/file_processor.py
embeddingframework/utils/__init__.py
embeddingframework/utils/file_utils.py
embeddingframework/utils/preprocessing.py
embeddingframework/utils/retry.py
embeddingframework/utils/splitters.py
embeddingframework-1.0.8.dist-info/licenses/LICENSE
embeddingframework-1.0.8.dist-info/METADATA
embeddingframework-1.0.8.dist-info/WHEEL
embeddingframework-1.0.8.dist-info/entry_points.txt
embeddingframework-1.0.8.dist-info/top_level.txt
embeddingframework-1.0.8.dist-info/RECORD
