Metadata-Version: 2.4
Name: embeddingframework
Version: 1.0.8
Summary: A high-performance, asynchronous, and extensible Python package for processing files, generating embeddings, and storing them in various vector databases with optional cloud storage integration.
Home-page: https://github.com/isathish/embeddingframework
Author: SathishKumar Nagarajan
Author-email: mail@sathishkumarnagarajan.com
Classifier: Programming Language :: Python :: 3
Classifier: License :: OSI Approved :: MIT License
Classifier: Operating System :: OS Independent
Requires-Python: >=3.7
License-File: LICENSE
Requires-Dist: aiofiles
Requires-Dist: asyncio
Requires-Dist: argparse
Requires-Dist: pytest
Requires-Dist: pytest-cov
Requires-Dist: chromadb
Requires-Dist: faiss-cpu
Requires-Dist: pymilvus
Requires-Dist: openai
Requires-Dist: weaviate-client
Requires-Dist: PyPDF2
Requires-Dist: python-docx
Requires-Dist: boto3
Requires-Dist: google-cloud-storage
Requires-Dist: azure-storage-blob
Requires-Dist: openpyxl
Dynamic: author
Dynamic: author-email
Dynamic: classifier
Dynamic: description
Dynamic: description-content-type
Dynamic: home-page
Dynamic: license-file
Dynamic: requires-dist
Dynamic: requires-python
Dynamic: summary
